{
  "ts": "2026-04-10T17:34:22.081779+09:00",
  "start_date": "2026-04-01",
  "status": "running",
  "equity": 30103.72,
  "available": 24978.02,
  "unrealized": -218.8,
  "daily_pnl": 124.45,
  "total_pnl": 103.72,
  "cum_pct": 0.35,
  "daily_avg_pct": 0.035,
  "annual_pct": 13.62,
  "mdd": -10.32,
  "current_dd": -0.52,
  "seed_used": 5125.7,
  "seed_used_pct": 17.03,
  "long_count": 8,
  "short_count": 2,
  "positions": [
    {
      "symbol": "SOLUSDT",
      "side": "SHORT",
      "pnl": 4.95,
      "pnl_pct": 0.08,
      "margin": 1270.52,
      "leverage": "5",
      "tier": "8/9",
      "entry": 83.0407,
      "mark": 82.976
    },
    {
      "symbol": "BCHUSDT",
      "side": "LONG",
      "pnl": -34.3,
      "pnl_pct": -0.56,
      "margin": 617.97,
      "leverage": "10",
      "tier": "5/9",
      "entry": 438.5844,
      "mark": 436.15
    },
    {
      "symbol": "XRPUSDT",
      "side": "LONG",
      "pnl": -12.17,
      "pnl_pct": -0.25,
      "margin": 408.94,
      "leverage": "12",
      "tier": "3/9",
      "entry": 1.3444,
      "mark": 1.3411
    },
    {
      "symbol": "ALGOUSDT",
      "side": "LONG",
      "pnl": -144.99,
      "pnl_pct": -9.28,
      "margin": 312.63,
      "leverage": "5",
      "tier": "4/11",
      "entry": 0.1214,
      "mark": 0.1101
    },
    {
      "symbol": "BNBUSDT",
      "side": "LONG",
      "pnl": -39.04,
      "pnl_pct": -1.43,
      "margin": 303.47,
      "leverage": "9",
      "tier": "6/9",
      "entry": 608.2853,
      "mark": 599.59
    },
    {
      "symbol": "DOGEUSDT",
      "side": "LONG",
      "pnl": -2.23,
      "pnl_pct": -0.12,
      "margin": 205.23,
      "leverage": "9",
      "tier": "3/9",
      "entry": 0.0923,
      "mark": 0.0921
    },
    {
      "symbol": "BTCUSDT",
      "side": "LONG",
      "pnl": 0.1,
      "pnl_pct": 0.01,
      "margin": 151.17,
      "leverage": "9",
      "tier": "3/9",
      "entry": 71606.1158,
      "mark": 71611.45
    },
    {
      "symbol": "LTCUSDT",
      "side": "LONG",
      "pnl": -1.66,
      "pnl_pct": -0.24,
      "margin": 99.64,
      "leverage": "7",
      "tier": "2/9",
      "entry": 54.4898,
      "mark": 54.36
    },
    {
      "symbol": "AAVEUSDT",
      "side": "SHORT",
      "pnl": 8.32,
      "pnl_pct": 0.98,
      "margin": 84.58,
      "leverage": "10",
      "tier": "2/9",
      "entry": 90.46,
      "mark": 89.57
    },
    {
      "symbol": "SUIUSDT",
      "side": "LONG",
      "pnl": 2.24,
      "pnl_pct": 0.36,
      "margin": 77.85,
      "leverage": "8",
      "tier": "2/9",
      "entry": 0.9295,
      "mark": 0.9328
    }
  ],
  "signals": {
    "BTCUSDT": {
      "dir": "long",
      "conf": 0.792
    },
    "XRPUSDT": {
      "dir": "short",
      "conf": 0.521
    },
    "SOLUSDT": {
      "dir": "short",
      "conf": 0.582
    },
    "LINKUSDT": {
      "dir": "short",
      "conf": 0.538
    },
    "1000PEPEUSDT": {
      "dir": "short",
      "conf": 0.523
    },
    "HYPEUSDT": {
      "dir": "short",
      "conf": 0.539
    },
    "ADAUSDT": {
      "dir": "short",
      "conf": 0.65
    },
    "SUIUSDT": {
      "dir": "long",
      "conf": 0.747
    },
    "ETHUSDT": {
      "dir": "short",
      "conf": 0.552
    },
    "DOGEUSDT": {
      "dir": "long",
      "conf": 0.591
    },
    "TAOUSDT": {
      "dir": "short",
      "conf": 0.509
    },
    "BNBUSDT": {
      "dir": "short",
      "conf": 0.603
    },
    "DOTUSDT": {
      "dir": "short",
      "conf": 0.716
    },
    "AAVEUSDT": {
      "dir": "long",
      "conf": 0.508
    },
    "AVAXUSDT": {
      "dir": "short",
      "conf": 0.724
    },
    "NEARUSDT": {
      "dir": "short",
      "conf": 0.5
    },
    "ENAUSDT": {
      "dir": "short",
      "conf": 0.543
    },
    "UNIUSDT": {
      "dir": "short",
      "conf": 0.596
    },
    "STABLEUSDT": {
      "dir": "long",
      "conf": 0.617
    },
    "LTCUSDT": {
      "dir": "short",
      "conf": 0.514
    },
    "ZECUSDT": {
      "dir": "long",
      "conf": 0.502
    },
    "ARBUSDT": {
      "dir": "short",
      "conf": 0.508
    },
    "ALGOUSDT": {
      "dir": "short",
      "conf": 0.528
    },
    "TRUMPUSDT": {
      "dir": "short",
      "conf": 0.581
    },
    "WLDUSDT": {
      "dir": "long",
      "conf": 0.674
    },
    "BCHUSDT": {
      "dir": "long",
      "conf": 0.745
    },
    "XMRUSDT": {
      "dir": "short",
      "conf": 0.567
    },
    "TONUSDT": {
      "dir": "long",
      "conf": 0.521
    }
  },
  "equity_hist": [
    {
      "t": "2026-04-01",
      "v": 0.61
    },
    {
      "t": "2026-04-02",
      "v": 37.46
    },
    {
      "t": "2026-04-03",
      "v": 73.47
    },
    {
      "t": "2026-04-04",
      "v": 82.06
    },
    {
      "t": "2026-04-05",
      "v": 153.76
    },
    {
      "t": "2026-04-06",
      "v": 168.46
    },
    {
      "t": "2026-04-07",
      "v": -104.95
    },
    {
      "t": "2026-04-08",
      "v": -293.36
    },
    {
      "t": "2026-04-09",
      "v": -257.9
    },
    {
      "t": "2026-04-10",
      "v": -226.96
    }
  ],
  "trade_history": [
    {
      "ts": "2026-04-10 17:27",
      "symbol": "DOTUSDT",
      "side": "Buy",
      "pnl": 0.0,
      "reason": "1/9"
    },
    {
      "ts": "2026-04-10 17:23",
      "symbol": "DOTUSDT",
      "side": "Buy",
      "pnl": 0.26,
      "reason": "1/9"
    },
    {
      "ts": "2026-04-10 17:09",
      "symbol": "DOTUSDT",
      "side": "Buy",
      "pnl": 0.53,
      "reason": "2/9"
    },
    {
      "ts": "2026-04-10 14:45",
      "symbol": "ADAUSDT",
      "side": "Buy",
      "pnl": -0.11,
      "reason": "2/10"
    },
    {
      "ts": "2026-04-10 14:27",
      "symbol": "ADAUSDT",
      "side": "Buy",
      "pnl": 0.86,
      "reason": "3/10"
    },
    {
      "ts": "2026-04-10 13:54",
      "symbol": "AAVEUSDT",
      "side": "Sell",
      "pnl": 9.24,
      "reason": "5/9"
    },
    {
      "ts": "2026-04-10 12:20",
      "symbol": "AAVEUSDT",
      "side": "Sell",
      "pnl": 16.72,
      "reason": "5/9"
    },
    {
      "ts": "2026-04-10 12:19",
      "symbol": "AAVEUSDT",
      "side": "Sell",
      "pnl": 32.24,
      "reason": "-"
    },
    {
      "ts": "2026-04-10 12:10",
      "symbol": "BCHUSDT",
      "side": "Sell",
      "pnl": -0.08,
      "reason": "4/9"
    },
    {
      "ts": "2026-04-10 12:09",
      "symbol": "DOTUSDT",
      "side": "Buy",
      "pnl": -0.0,
      "reason": "4/9"
    },
    {
      "ts": "2026-04-10 12:09",
      "symbol": "BCHUSDT",
      "side": "Sell",
      "pnl": -35.92,
      "reason": "4/9"
    },
    {
      "ts": "2026-04-10 12:02",
      "symbol": "DOTUSDT",
      "side": "Buy",
      "pnl": -5.48,
      "reason": "2/10"
    },
    {
      "ts": "2026-04-10 11:52",
      "symbol": "BCHUSDT",
      "side": "Sell",
      "pnl": -40.51,
      "reason": "1/9"
    },
    {
      "ts": "2026-04-10 11:51",
      "symbol": "AVAXUSDT",
      "side": "Buy",
      "pnl": 0.0,
      "reason": "1/9"
    },
    {
      "ts": "2026-04-10 11:47",
      "symbol": "AVAXUSDT",
      "side": "Buy",
      "pnl": 2.03,
      "reason": "2/10"
    },
    {
      "ts": "2026-04-10 11:33",
      "symbol": "AVAXUSDT",
      "side": "Buy",
      "pnl": 4.42,
      "reason": "3/10"
    },
    {
      "ts": "2026-04-10 08:53",
      "symbol": "LTCUSDT",
      "side": "Sell",
      "pnl": 0.0,
      "reason": "1/9"
    },
    {
      "ts": "2026-04-10 08:49",
      "symbol": "LTCUSDT",
      "side": "Sell",
      "pnl": 1.85,
      "reason": "5/9"
    },
    {
      "ts": "2026-04-10 08:33",
      "symbol": "ADAUSDT",
      "side": "Sell",
      "pnl": 24.5,
      "reason": "6/9"
    },
    {
      "ts": "2026-04-10 08:33",
      "symbol": "LTCUSDT",
      "side": "Sell",
      "pnl": 0.58,
      "reason": "6/9"
    }
  ],
  "num_days": 10
}