{
  "ts": "2026-05-04T07:39:00.401536+09:00",
  "start_date": "2026-04-01",
  "status": "running",
  "equity": 84485.15,
  "available": 67798.44,
  "unrealized": -141.42,
  "daily_pnl": 124.16,
  "total_pnl": 4485.15,
  "cum_pct": 5.61,
  "daily_avg_pct": 0.1607,
  "annual_pct": 79.69,
  "mdd": -10.32,
  "current_dd": -1.69,
  "seed_used": 16686.71,
  "seed_used_pct": 19.75,
  "long_count": 10,
  "short_count": 5,
  "positions": [
    {
      "symbol": "ONDOUSDT",
      "side": "SHORT",
      "pnl": -275.99,
      "pnl_pct": -1.28,
      "margin": 3108.86,
      "leverage": "7",
      "tier": "7/9",
      "entry": 0.2855,
      "mark": 0.2892
    },
    {
      "symbol": "WLDUSDT",
      "side": "SHORT",
      "pnl": -134.12,
      "pnl_pct": -1.07,
      "margin": 1811.11,
      "leverage": "7",
      "tier": "5/9",
      "entry": 0.2374,
      "mark": 0.2399
    },
    {
      "symbol": "BCHUSDT",
      "side": "LONG",
      "pnl": 26.91,
      "pnl_pct": 0.36,
      "margin": 842.56,
      "leverage": "9",
      "tier": "3/9",
      "entry": 444.2182,
      "mark": 445.8
    },
    {
      "symbol": "XRPUSDT",
      "side": "LONG",
      "pnl": 38.84,
      "pnl_pct": 0.78,
      "margin": 626.37,
      "leverage": "8",
      "tier": "3/9",
      "entry": 1.3866,
      "mark": 1.3974
    },
    {
      "symbol": "DOGEUSDT",
      "side": "LONG",
      "pnl": 28.98,
      "pnl_pct": 0.88,
      "margin": 554.88,
      "leverage": "6",
      "tier": "3/9",
      "entry": 0.1082,
      "mark": 0.1091
    },
    {
      "symbol": "TAOUSDT",
      "side": "LONG",
      "pnl": -19.27,
      "pnl_pct": -0.56,
      "margin": 424.42,
      "leverage": "8",
      "tier": "3/10",
      "entry": 291.254,
      "mark": 289.61
    },
    {
      "symbol": "LINKUSDT",
      "side": "LONG",
      "pnl": 32.1,
      "pnl_pct": 0.79,
      "margin": 409.16,
      "leverage": "10",
      "tier": "2/9",
      "entry": 9.106,
      "mark": 9.178
    },
    {
      "symbol": "ADAUSDT",
      "side": "SHORT",
      "pnl": 2.21,
      "pnl_pct": 0.08,
      "margin": 346.01,
      "leverage": "8",
      "tier": "2/9",
      "entry": 0.251,
      "mark": 0.2508
    },
    {
      "symbol": "AVAXUSDT",
      "side": "LONG",
      "pnl": 27.3,
      "pnl_pct": 1.03,
      "margin": 335.88,
      "leverage": "8",
      "tier": "2/9",
      "entry": 9.059,
      "mark": 9.152
    },
    {
      "symbol": "TONUSDT",
      "side": "LONG",
      "pnl": 47.18,
      "pnl_pct": 1.94,
      "margin": 310.33,
      "leverage": "8",
      "tier": "1/9",
      "entry": 1.3267,
      "mark": 1.3524
    },
    {
      "symbol": "SUIUSDT",
      "side": "LONG",
      "pnl": 28.43,
      "pnl_pct": 1.16,
      "margin": 309.15,
      "leverage": "8",
      "tier": "2/9",
      "entry": 0.9157,
      "mark": 0.9263
    },
    {
      "symbol": "DOTUSDT",
      "side": "SHORT",
      "pnl": 1.04,
      "pnl_pct": 0.06,
      "margin": 257.73,
      "leverage": "7",
      "tier": "1/9",
      "entry": 1.2205,
      "mark": 1.2198
    },
    {
      "symbol": "ARBUSDT",
      "side": "LONG",
      "pnl": 14.62,
      "pnl_pct": 1.08,
      "margin": 227.86,
      "leverage": "6",
      "tier": "2/10",
      "entry": 0.1175,
      "mark": 0.1188
    },
    {
      "symbol": "WLFIUSDT",
      "side": "SHORT",
      "pnl": -5.93,
      "pnl_pct": -0.46,
      "margin": 216.16,
      "leverage": "6",
      "tier": "2/10",
      "entry": 0.0588,
      "mark": 0.059
    },
    {
      "symbol": "PENGUUSDT",
      "side": "LONG",
      "pnl": 46.28,
      "pnl_pct": 2.8,
      "margin": 212.26,
      "leverage": "8",
      "tier": "4/10",
      "entry": 0.0098,
      "mark": 0.0101
    }
  ],
  "signals": {
    "BTCUSDT": {
      "dir": "short",
      "conf": 0.508
    },
    "XRPUSDT": {
      "dir": "short",
      "conf": 0.503
    },
    "SOLUSDT": {
      "dir": "short",
      "conf": 0.563
    },
    "LINKUSDT": {
      "dir": "short",
      "conf": 0.575
    },
    "1000PEPEUSDT": {
      "dir": "short",
      "conf": 0.514
    },
    "HYPEUSDT": {
      "dir": "long",
      "conf": 0.502
    },
    "ADAUSDT": {
      "dir": "short",
      "conf": 0.713
    },
    "SUIUSDT": {
      "dir": "short",
      "conf": 0.54
    },
    "ETHUSDT": {
      "dir": "long",
      "conf": 0.511
    },
    "DOGEUSDT": {
      "dir": "long",
      "conf": 0.582
    },
    "TAOUSDT": {
      "dir": "long",
      "conf": 0.599
    },
    "BNBUSDT": {
      "dir": "short",
      "conf": 0.501
    },
    "DOTUSDT": {
      "dir": "short",
      "conf": 0.676
    },
    "AAVEUSDT": {
      "dir": "short",
      "conf": 0.51
    },
    "AVAXUSDT": {
      "dir": "long",
      "conf": 0.501
    },
    "NEARUSDT": {
      "dir": "short",
      "conf": 0.52
    },
    "ENAUSDT": {
      "dir": "short",
      "conf": 0.508
    },
    "UNIUSDT": {
      "dir": "short",
      "conf": 0.596
    },
    "STABLEUSDT": {
      "dir": "short",
      "conf": 0.592
    },
    "LTCUSDT": {
      "dir": "short",
      "conf": 0.508
    },
    "ZECUSDT": {
      "dir": "short",
      "conf": 0.537
    },
    "ARBUSDT": {
      "dir": "long",
      "conf": 0.586
    },
    "ALGOUSDT": {
      "dir": "short",
      "conf": 0.529
    },
    "TRUMPUSDT": {
      "dir": "short",
      "conf": 0.549
    },
    "WLDUSDT": {
      "dir": "short",
      "conf": 0.517
    },
    "BCHUSDT": {
      "dir": "short",
      "conf": 0.758
    },
    "XMRUSDT": {
      "dir": "short",
      "conf": 0.555
    },
    "TONUSDT": {
      "dir": "short",
      "conf": 0.523
    },
    "WLFIUSDT": {
      "dir": "short",
      "conf": 0.632
    },
    "DASHUSDT": {
      "dir": "long",
      "conf": 0.545
    },
    "RAVEUSDT": {
      "dir": "long",
      "conf": 0.754
    },
    "ASTERUSDT": {
      "dir": "short",
      "conf": 0.628
    },
    "SIRENUSDT": {
      "dir": "short",
      "conf": 0.563
    },
    "1000BONKUSDT": {
      "dir": "short",
      "conf": 0.529
    },
    "MUSDT": {
      "dir": "short",
      "conf": 0.538
    },
    "MNTUSDT": {
      "dir": "long",
      "conf": 0.504
    },
    "TRXUSDT": {
      "dir": "short",
      "conf": 0.621
    },
    "PENGUUSDT": {
      "dir": "long",
      "conf": 0.643
    },
    "APTUSDT": {
      "dir": "short",
      "conf": 0.696
    },
    "ONDOUSDT": {
      "dir": "long",
      "conf": 0.54
    }
  },
  "equity_hist": [
    {
      "t": "2026-04-14",
      "v": 664.4
    },
    {
      "t": "2026-04-15",
      "v": 605.46
    },
    {
      "t": "2026-04-16",
      "v": 1031.24
    },
    {
      "t": "2026-04-17",
      "v": 1373.66
    },
    {
      "t": "2026-04-18",
      "v": 1434.8
    },
    {
      "t": "2026-04-19",
      "v": 1362.33
    },
    {
      "t": "2026-04-20",
      "v": 1411.76
    },
    {
      "t": "2026-04-21",
      "v": 1665.55
    },
    {
      "t": "2026-04-22",
      "v": 1726.96
    },
    {
      "t": "2026-04-23",
      "v": 2433.14
    },
    {
      "t": "2026-04-24",
      "v": 2827.79
    },
    {
      "t": "2026-04-25",
      "v": 3139.96
    },
    {
      "t": "2026-04-26",
      "v": 3637.21
    },
    {
      "t": "2026-04-27",
      "v": 3874.96
    },
    {
      "t": "2026-04-28",
      "v": 4396.16
    },
    {
      "t": "2026-04-29",
      "v": 4947.79
    },
    {
      "t": "2026-04-30",
      "v": 5309.31
    },
    {
      "t": "2026-05-01",
      "v": 5478.65
    },
    {
      "t": "2026-05-02",
      "v": 4739.79
    },
    {
      "t": "2026-05-03",
      "v": 4532.76
    },
    {
      "t": "2026-05-04",
      "v": 4485.15
    }
  ],
  "trade_history": [
    {
      "ts": "2026-05-04 07:37",
      "symbol": "PENGUUSDT",
      "side": "Buy",
      "pnl": 44.61,
      "reason": "4/10"
    },
    {
      "ts": "2026-05-04 07:35",
      "symbol": "PENGUUSDT",
      "side": "Buy",
      "pnl": 97.66,
      "reason": "-"
    },
    {
      "ts": "2026-05-04 07:32",
      "symbol": "APTUSDT",
      "side": "Buy",
      "pnl": -0.16,
      "reason": "1/9"
    },
    {
      "ts": "2026-05-04 07:17",
      "symbol": "SOLUSDT",
      "side": "Sell",
      "pnl": -0.05,
      "reason": "마진 0.8USDT < 48"
    },
    {
      "ts": "2026-05-04 07:15",
      "symbol": "SOLUSDT",
      "side": "Sell",
      "pnl": -118.85,
      "reason": "4/9"
    },
    {
      "ts": "2026-05-04 07:14",
      "symbol": "APTUSDT",
      "side": "Buy",
      "pnl": 2.0,
      "reason": "1/9"
    },
    {
      "ts": "2026-05-04 06:45",
      "symbol": "1000PEPEUSDT",
      "side": "Sell",
      "pnl": 62.22,
      "reason": "5/10"
    },
    {
      "ts": "2026-05-04 06:37",
      "symbol": "APTUSDT",
      "side": "Sell",
      "pnl": 0.0,
      "reason": "1/9"
    },
    {
      "ts": "2026-05-04 06:37",
      "symbol": "APTUSDT",
      "side": "Sell",
      "pnl": 2.95,
      "reason": "1/9"
    },
    {
      "ts": "2026-05-04 06:23",
      "symbol": "APTUSDT",
      "side": "Sell",
      "pnl": 0.82,
      "reason": "1/9"
    },
    {
      "ts": "2026-05-04 05:28",
      "symbol": "DOTUSDT",
      "side": "Sell",
      "pnl": 0.0,
      "reason": "L2"
    },
    {
      "ts": "2026-05-04 05:24",
      "symbol": "DOTUSDT",
      "side": "Sell",
      "pnl": 32.97,
      "reason": "1/9"
    },
    {
      "ts": "2026-05-03 22:00",
      "symbol": "ARBUSDT",
      "side": "Sell",
      "pnl": 2.2,
      "reason": "1/11"
    },
    {
      "ts": "2026-05-03 21:45",
      "symbol": "ARBUSDT",
      "side": "Sell",
      "pnl": 0.24,
      "reason": "2/11"
    },
    {
      "ts": "2026-05-03 20:47",
      "symbol": "APTUSDT",
      "side": "Sell",
      "pnl": 0.0,
      "reason": "L2"
    },
    {
      "ts": "2026-05-03 20:43",
      "symbol": "APTUSDT",
      "side": "Sell",
      "pnl": 9.75,
      "reason": "2/9"
    },
    {
      "ts": "2026-05-03 17:57",
      "symbol": "MUSDT",
      "side": "Sell",
      "pnl": -24.6,
      "reason": "3/10"
    },
    {
      "ts": "2026-05-03 17:49",
      "symbol": "ONDOUSDT",
      "side": "Sell",
      "pnl": 82.95,
      "reason": "3/10"
    },
    {
      "ts": "2026-05-03 15:11",
      "symbol": "TRXUSDT",
      "side": "Buy",
      "pnl": 135.91,
      "reason": "2/9"
    },
    {
      "ts": "2026-05-03 11:57",
      "symbol": "MUSDT",
      "side": "Buy",
      "pnl": -5.22,
      "reason": "2/11"
    }
  ],
  "num_days": 34
}