{
  "ts": "2026-04-24T02:09:25.795664+09:00",
  "start_date": "2026-04-01",
  "status": "running",
  "equity": 32454.04,
  "available": 25367.91,
  "unrealized": -316.51,
  "daily_pnl": 22.73,
  "total_pnl": 2454.04,
  "cum_pct": 8.18,
  "daily_avg_pct": 0.3408,
  "annual_pct": 246.19,
  "mdd": -10.32,
  "current_dd": -0.01,
  "seed_used": 7086.13,
  "seed_used_pct": 21.83,
  "long_count": 6,
  "short_count": 8,
  "positions": [
    {
      "symbol": "BTCUSDT",
      "side": "SHORT",
      "pnl": -63.51,
      "pnl_pct": -0.59,
      "margin": 1360.55,
      "leverage": "8",
      "tier": "9/9",
      "entry": 77291.8364,
      "mark": 77745.5
    },
    {
      "symbol": "BCHUSDT",
      "side": "LONG",
      "pnl": -20.1,
      "pnl_pct": -0.28,
      "margin": 705.59,
      "leverage": "10",
      "tier": "6/9",
      "entry": 457.399,
      "mark": 456.1
    },
    {
      "symbol": "LINKUSDT",
      "side": "LONG",
      "pnl": -115.62,
      "pnl_pct": -2.03,
      "margin": 698.44,
      "leverage": "8",
      "tier": "7/10",
      "entry": 9.4485,
      "mark": 9.257
    },
    {
      "symbol": "TRXUSDT",
      "side": "LONG",
      "pnl": 6.24,
      "pnl_pct": 0.16,
      "margin": 491.67,
      "leverage": "8",
      "tier": "4/9",
      "entry": 0.3284,
      "mark": 0.329
    },
    {
      "symbol": "ADAUSDT",
      "side": "LONG",
      "pnl": -138.45,
      "pnl_pct": -5.32,
      "margin": 352.23,
      "leverage": "7",
      "tier": "4/10",
      "entry": 0.2615,
      "mark": 0.2476
    },
    {
      "symbol": "DOGEUSDT",
      "side": "LONG",
      "pnl": -89.5,
      "pnl_pct": -3.17,
      "margin": 342.27,
      "leverage": "8",
      "tier": "4/10",
      "entry": 0.0996,
      "mark": 0.0965
    },
    {
      "symbol": "ARBUSDT",
      "side": "SHORT",
      "pnl": 20.11,
      "pnl_pct": 0.9,
      "margin": 317.97,
      "leverage": "7",
      "tier": "3/9",
      "entry": 0.1279,
      "mark": 0.1268
    },
    {
      "symbol": "WLDUSDT",
      "side": "SHORT",
      "pnl": 14.63,
      "pnl_pct": 0.8,
      "margin": 200.41,
      "leverage": "9",
      "tier": "2/9",
      "entry": 0.2621,
      "mark": 0.26
    },
    {
      "symbol": "TAOUSDT",
      "side": "SHORT",
      "pnl": 20.62,
      "pnl_pct": 1.58,
      "margin": 183.07,
      "leverage": "7",
      "tier": "3/9",
      "entry": 245.7209,
      "mark": 241.83
    },
    {
      "symbol": "DOTUSDT",
      "side": "SHORT",
      "pnl": 36.3,
      "pnl_pct": 2.77,
      "margin": 181.71,
      "leverage": "7",
      "tier": "2/9",
      "entry": 1.2718,
      "mark": 1.2365
    },
    {
      "symbol": "ENAUSDT",
      "side": "LONG",
      "pnl": -1.84,
      "pnl_pct": -0.22,
      "margin": 94.35,
      "leverage": "9",
      "tier": "2/9",
      "entry": 0.1065,
      "mark": 0.1063
    },
    {
      "symbol": "XRPUSDT",
      "side": "SHORT",
      "pnl": -0.36,
      "pnl_pct": -0.05,
      "margin": 91.84,
      "leverage": "8",
      "tier": "1/9",
      "entry": 1.4265,
      "mark": 1.4272
    },
    {
      "symbol": "1000PEPEUSDT",
      "side": "SHORT",
      "pnl": 12.44,
      "pnl_pct": 1.75,
      "margin": 87.51,
      "leverage": "8",
      "tier": "2/9",
      "entry": 0.0038,
      "mark": 0.0038
    },
    {
      "symbol": "ZECUSDT",
      "side": "SHORT",
      "pnl": 2.65,
      "pnl_pct": 0.61,
      "margin": 61.36,
      "leverage": "7",
      "tier": "2/11",
      "entry": 324.95,
      "mark": 322.96
    }
  ],
  "signals": {
    "BTCUSDT": {
      "dir": "short",
      "conf": 0.581
    },
    "XRPUSDT": {
      "dir": "short",
      "conf": 0.562
    },
    "SOLUSDT": {
      "dir": "long",
      "conf": 0.59
    },
    "LINKUSDT": {
      "dir": "long",
      "conf": 0.512
    },
    "1000PEPEUSDT": {
      "dir": "long",
      "conf": 0.631
    },
    "HYPEUSDT": {
      "dir": "long",
      "conf": 0.508
    },
    "ADAUSDT": {
      "dir": "short",
      "conf": 0.544
    },
    "SUIUSDT": {
      "dir": "long",
      "conf": 0.505
    },
    "ETHUSDT": {
      "dir": "long",
      "conf": 0.521
    },
    "DOGEUSDT": {
      "dir": "short",
      "conf": 0.504
    },
    "TAOUSDT": {
      "dir": "short",
      "conf": 0.53
    },
    "BNBUSDT": {
      "dir": "short",
      "conf": 0.519
    },
    "DOTUSDT": {
      "dir": "short",
      "conf": 0.517
    },
    "AAVEUSDT": {
      "dir": "short",
      "conf": 0.537
    },
    "AVAXUSDT": {
      "dir": "long",
      "conf": 0.687
    },
    "NEARUSDT": {
      "dir": "short",
      "conf": 0.508
    },
    "ENAUSDT": {
      "dir": "long",
      "conf": 0.674
    },
    "UNIUSDT": {
      "dir": "short",
      "conf": 0.596
    },
    "STABLEUSDT": {
      "dir": "long",
      "conf": 0.617
    },
    "LTCUSDT": {
      "dir": "short",
      "conf": 0.607
    },
    "ZECUSDT": {
      "dir": "short",
      "conf": 0.643
    },
    "ARBUSDT": {
      "dir": "short",
      "conf": 0.528
    },
    "ALGOUSDT": {
      "dir": "short",
      "conf": 0.529
    },
    "TRUMPUSDT": {
      "dir": "short",
      "conf": 0.582
    },
    "WLDUSDT": {
      "dir": "long",
      "conf": 0.511
    },
    "BCHUSDT": {
      "dir": "long",
      "conf": 0.594
    },
    "XMRUSDT": {
      "dir": "short",
      "conf": 0.567
    },
    "TONUSDT": {
      "dir": "long",
      "conf": 0.504
    },
    "WLFIUSDT": {
      "dir": "short",
      "conf": 0.523
    },
    "DASHUSDT": {
      "dir": "long",
      "conf": 0.545
    },
    "RAVEUSDT": {
      "dir": "long",
      "conf": 0.754
    },
    "ASTERUSDT": {
      "dir": "long",
      "conf": 0.534
    },
    "SIRENUSDT": {
      "dir": "short",
      "conf": 0.563
    },
    "1000BONKUSDT": {
      "dir": "short",
      "conf": 0.529
    },
    "MUSDT": {
      "dir": "short",
      "conf": 0.749
    },
    "MNTUSDT": {
      "dir": "long",
      "conf": 0.504
    },
    "TRXUSDT": {
      "dir": "long",
      "conf": 0.691
    },
    "PENGUUSDT": {
      "dir": "short",
      "conf": 0.583
    }
  },
  "equity_hist": [
    {
      "t": "2026-04-14",
      "v": 664.4
    },
    {
      "t": "2026-04-15",
      "v": 605.46
    },
    {
      "t": "2026-04-16",
      "v": 1031.24
    },
    {
      "t": "2026-04-17",
      "v": 1373.66
    },
    {
      "t": "2026-04-18",
      "v": 1434.8
    },
    {
      "t": "2026-04-19",
      "v": 1362.33
    },
    {
      "t": "2026-04-20",
      "v": 1411.76
    },
    {
      "t": "2026-04-21",
      "v": 1665.55
    },
    {
      "t": "2026-04-22",
      "v": 1726.96
    },
    {
      "t": "2026-04-23",
      "v": 2433.14
    },
    {
      "t": "2026-04-24",
      "v": 2454.04
    }
  ],
  "trade_history": [
    {
      "ts": "2026-04-24 02:02",
      "symbol": "AVAXUSDT",
      "side": "Buy",
      "pnl": 1.77,
      "reason": "1/9"
    },
    {
      "ts": "2026-04-24 00:52",
      "symbol": "SOLUSDT",
      "side": "Sell",
      "pnl": 0.28,
      "reason": "마진 1.2USDT < 17"
    },
    {
      "ts": "2026-04-24 00:50",
      "symbol": "SOLUSDT",
      "side": "Sell",
      "pnl": 20.68,
      "reason": "2/9"
    },
    {
      "ts": "2026-04-24 00:03",
      "symbol": "XRPUSDT",
      "side": "Sell",
      "pnl": -0.0,
      "reason": "L2"
    },
    {
      "ts": "2026-04-23 23:58",
      "symbol": "XRPUSDT",
      "side": "Sell",
      "pnl": -5.99,
      "reason": "1/9"
    },
    {
      "ts": "2026-04-23 21:52",
      "symbol": "ZECUSDT",
      "side": "Buy",
      "pnl": 0.09,
      "reason": "마진 0.5USDT < 17"
    },
    {
      "ts": "2026-04-23 21:47",
      "symbol": "ZECUSDT",
      "side": "Buy",
      "pnl": 60.3,
      "reason": "4/9"
    },
    {
      "ts": "2026-04-23 21:32",
      "symbol": "1000PEPEUSDT",
      "side": "Sell",
      "pnl": 6.63,
      "reason": "3/9"
    },
    {
      "ts": "2026-04-23 18:10",
      "symbol": "XMRUSDT",
      "side": "Buy",
      "pnl": 7.7,
      "reason": "L4"
    },
    {
      "ts": "2026-04-23 18:03",
      "symbol": "XMRUSDT",
      "side": "Buy",
      "pnl": 16.53,
      "reason": "6/9"
    },
    {
      "ts": "2026-04-23 18:03",
      "symbol": "XMRUSDT",
      "side": "Buy",
      "pnl": 33.34,
      "reason": "6/9"
    },
    {
      "ts": "2026-04-23 16:32",
      "symbol": "PENGUUSDT",
      "side": "Buy",
      "pnl": 5.02,
      "reason": "2/12"
    },
    {
      "ts": "2026-04-23 15:54",
      "symbol": "ZECUSDT",
      "side": "Sell",
      "pnl": -1.6,
      "reason": "1/11"
    },
    {
      "ts": "2026-04-23 15:10",
      "symbol": "XRPUSDT",
      "side": "Sell",
      "pnl": 0.0,
      "reason": "T1 진입 | GF=6 | Lv=8x | Seed=$2336(7.3%)"
    },
    {
      "ts": "2026-04-23 15:07",
      "symbol": "XRPUSDT",
      "side": "Sell",
      "pnl": 12.13,
      "reason": "2/10"
    },
    {
      "ts": "2026-04-23 15:06",
      "symbol": "1000PEPEUSDT",
      "side": "Sell",
      "pnl": -1.04,
      "reason": "2/10"
    },
    {
      "ts": "2026-04-23 15:02",
      "symbol": "1000PEPEUSDT",
      "side": "Sell",
      "pnl": 0.09,
      "reason": "-"
    },
    {
      "ts": "2026-04-23 14:28",
      "symbol": "PENGUUSDT",
      "side": "Buy",
      "pnl": 8.03,
      "reason": "3/11"
    },
    {
      "ts": "2026-04-23 13:37",
      "symbol": "PENGUUSDT",
      "side": "Buy",
      "pnl": 7.53,
      "reason": "3/11"
    },
    {
      "ts": "2026-04-23 13:32",
      "symbol": "PENGUUSDT",
      "side": "Buy",
      "pnl": 15.07,
      "reason": "-"
    }
  ],
  "num_days": 24
}