{
  "ts": "2026-06-30T20:20:43.676004+09:00",
  "start_date": "2026-04-01",
  "status": "running",
  "equity": 12888.64,
  "available": 7819.22,
  "unrealized": 4.34,
  "daily_pnl": -25.54,
  "total_pnl": -2111.36,
  "cum_pct": -14.08,
  "daily_avg_pct": -0.1666,
  "annual_pct": -45.59,
  "mdd": 0.0,
  "current_dd": 0.0,
  "seed_used": 5069.41,
  "seed_used_pct": 39.33,
  "long_count": 2,
  "short_count": 1,
  "positions": [
    {
      "symbol": "AAVEUSDT",
      "side": "SHORT",
      "pnl": 80.96,
      "pnl_pct": 1.3,
      "margin": 3071.83,
      "leverage": "2",
      "tier": "1/1",
      "entry": 89.8992,
      "mark": 88.73
    },
    {
      "symbol": "ONDOUSDT",
      "side": "LONG",
      "pnl": -26.4,
      "pnl_pct": -1.9,
      "margin": 682.22,
      "leverage": "2",
      "tier": "1/1",
      "entry": 0.3161,
      "mark": 0.3101
    },
    {
      "symbol": "ZECUSDT",
      "side": "LONG",
      "pnl": -50.31,
      "pnl_pct": -3.92,
      "margin": 616.12,
      "leverage": "2",
      "tier": "1/1",
      "entry": 405.87,
      "mark": 389.95
    }
  ],
  "signals": {},
  "equity_hist": [
    {
      "t": "2026-05-30",
      "v": 607.59
    },
    {
      "t": "2026-05-31",
      "v": 748.22
    },
    {
      "t": "2026-06-01",
      "v": 1014.93
    },
    {
      "t": "2026-06-02",
      "v": 1215.41
    },
    {
      "t": "2026-06-03",
      "v": 1100.21
    },
    {
      "t": "2026-06-04",
      "v": 1334.03
    },
    {
      "t": "2026-06-05",
      "v": 1581.46
    },
    {
      "t": "2026-06-06",
      "v": 1500.0
    },
    {
      "t": "2026-06-07",
      "v": 1495.16
    },
    {
      "t": "2026-06-08",
      "v": 944.66
    },
    {
      "t": "2026-06-09",
      "v": 1016.34
    },
    {
      "t": "2026-06-10",
      "v": 647.46
    },
    {
      "t": "2026-06-11",
      "v": 1881.31
    },
    {
      "t": "2026-06-12",
      "v": 663.72
    },
    {
      "t": "2026-06-13",
      "v": -11.73
    },
    {
      "t": "2026-06-14",
      "v": 435.9
    },
    {
      "t": "2026-06-15",
      "v": 353.8
    },
    {
      "t": "2026-06-16",
      "v": -80.52
    },
    {
      "t": "2026-06-17",
      "v": -725.91
    },
    {
      "t": "2026-06-18",
      "v": -1485.52
    },
    {
      "t": "2026-06-19",
      "v": -1577.51
    },
    {
      "t": "2026-06-20",
      "v": -2095.91
    },
    {
      "t": "2026-06-21",
      "v": -2098.44
    },
    {
      "t": "2026-06-22",
      "v": -2271.55
    },
    {
      "t": "2026-06-23",
      "v": -2277.26
    },
    {
      "t": "2026-06-24",
      "v": -2280.99
    },
    {
      "t": "2026-06-25",
      "v": -2282.37
    },
    {
      "t": "2026-06-26",
      "v": -2196.49
    },
    {
      "t": "2026-06-27",
      "v": -2116.59
    },
    {
      "t": "2026-06-28",
      "v": -1997.28
    },
    {
      "t": "2026-06-29",
      "v": -2053.06
    },
    {
      "t": "2026-06-30",
      "v": -2111.36
    }
  ],
  "trade_history": [
    {
      "ts": "2026-06-30 09:06",
      "symbol": "AAVEUSDT",
      "side": "Sell",
      "pnl": -25.54,
      "reason": "-"
    },
    {
      "ts": "2026-06-29 09:02",
      "symbol": "AAVEUSDT",
      "side": "Sell",
      "pnl": 93.03,
      "reason": "-"
    },
    {
      "ts": "2026-06-28 09:07",
      "symbol": "INJUSDT",
      "side": "Buy",
      "pnl": -67.83,
      "reason": "-"
    },
    {
      "ts": "2026-06-27 09:03",
      "symbol": "INJUSDT",
      "side": "Buy",
      "pnl": 169.7,
      "reason": "-"
    }
  ],
  "num_days": 91
}