{
  "ts": "2026-04-27T13:56:27.522676+09:00",
  "start_date": "2026-04-01",
  "status": "running",
  "equity": 83345.4,
  "available": 67657.22,
  "unrealized": -209.6,
  "daily_pnl": -250.68,
  "total_pnl": 3345.4,
  "cum_pct": 4.18,
  "daily_avg_pct": 0.1518,
  "annual_pct": 73.96,
  "mdd": -10.32,
  "current_dd": -0.65,
  "seed_used": 15688.18,
  "seed_used_pct": 18.82,
  "long_count": 7,
  "short_count": 7,
  "positions": [
    {
      "symbol": "ADAUSDT",
      "side": "SHORT",
      "pnl": -7.52,
      "pnl_pct": -0.07,
      "margin": 1503.71,
      "leverage": "7",
      "tier": "5/9",
      "entry": 0.2527,
      "mark": 0.2529
    },
    {
      "symbol": "BTCUSDT",
      "side": "SHORT",
      "pnl": -219.99,
      "pnl_pct": -2.03,
      "margin": 1380.11,
      "leverage": "8",
      "tier": "9/9",
      "entry": 77291.8364,
      "mark": 78863.22
    },
    {
      "symbol": "TRXUSDT",
      "side": "LONG",
      "pnl": -39.74,
      "pnl_pct": -0.47,
      "margin": 1051.25,
      "leverage": "8",
      "tier": "6/9",
      "entry": 0.3251,
      "mark": 0.3236
    },
    {
      "symbol": "SOLUSDT",
      "side": "SHORT",
      "pnl": -40.94,
      "pnl_pct": -0.36,
      "margin": 952.99,
      "leverage": "12",
      "tier": "3/9",
      "entry": 87.117,
      "mark": 87.43
    },
    {
      "symbol": "XMRUSDT",
      "side": "LONG",
      "pnl": -22.86,
      "pnl_pct": -0.45,
      "margin": 730.31,
      "leverage": "7",
      "tier": "4/10",
      "entry": 389.9055,
      "mark": 388.17
    },
    {
      "symbol": "ARBUSDT",
      "side": "LONG",
      "pnl": 60.99,
      "pnl_pct": 1.06,
      "margin": 724.14,
      "leverage": "8",
      "tier": "3/9",
      "entry": 0.1297,
      "mark": 0.131
    },
    {
      "symbol": "BCHUSDT",
      "side": "LONG",
      "pnl": -49.49,
      "pnl_pct": -0.7,
      "margin": 702.65,
      "leverage": "10",
      "tier": "6/9",
      "entry": 457.399,
      "mark": 454.2
    },
    {
      "symbol": "ASTERUSDT",
      "side": "SHORT",
      "pnl": 18.47,
      "pnl_pct": 0.5,
      "margin": 617.03,
      "leverage": "6",
      "tier": "3/9",
      "entry": 0.6617,
      "mark": 0.6584
    },
    {
      "symbol": "DOGEUSDT",
      "side": "LONG",
      "pnl": 36.63,
      "pnl_pct": 0.98,
      "margin": 540.91,
      "leverage": "7",
      "tier": "3/9",
      "entry": 0.0989,
      "mark": 0.0999
    },
    {
      "symbol": "XRPUSDT",
      "side": "SHORT",
      "pnl": -2.23,
      "pnl_pct": -0.05,
      "margin": 534.56,
      "leverage": "8",
      "tier": "3/9",
      "entry": 1.4374,
      "mark": 1.4381
    },
    {
      "symbol": "1000PEPEUSDT",
      "side": "SHORT",
      "pnl": -69.62,
      "pnl_pct": -2.33,
      "margin": 510.16,
      "leverage": "6",
      "tier": "4/9",
      "entry": 0.0039,
      "mark": 0.004
    },
    {
      "symbol": "SUIUSDT",
      "side": "LONG",
      "pnl": 75.76,
      "pnl_pct": 2.29,
      "margin": 376.18,
      "leverage": "9",
      "tier": "2/9",
      "entry": 0.935,
      "mark": 0.9564
    },
    {
      "symbol": "DOTUSDT",
      "side": "SHORT",
      "pnl": 1.39,
      "pnl_pct": 0.06,
      "margin": 313.53,
      "leverage": "8",
      "tier": "1/9",
      "entry": 1.2657,
      "mark": 1.265
    },
    {
      "symbol": "TAOUSDT",
      "side": "LONG",
      "pnl": 49.6,
      "pnl_pct": 4.21,
      "margin": 175.43,
      "leverage": "7",
      "tier": "3/9",
      "entry": 245.1891,
      "mark": 255.51
    }
  ],
  "signals": {
    "BTCUSDT": {
      "dir": "short",
      "conf": 0.507
    },
    "XRPUSDT": {
      "dir": "long",
      "conf": 0.584
    },
    "SOLUSDT": {
      "dir": "long",
      "conf": 0.716
    },
    "LINKUSDT": {
      "dir": "short",
      "conf": 0.523
    },
    "1000PEPEUSDT": {
      "dir": "short",
      "conf": 0.563
    },
    "HYPEUSDT": {
      "dir": "long",
      "conf": 0.512
    },
    "ADAUSDT": {
      "dir": "long",
      "conf": 0.58
    },
    "SUIUSDT": {
      "dir": "short",
      "conf": 0.912
    },
    "ETHUSDT": {
      "dir": "short",
      "conf": 0.502
    },
    "DOGEUSDT": {
      "dir": "long",
      "conf": 0.63
    },
    "TAOUSDT": {
      "dir": "short",
      "conf": 0.51
    },
    "BNBUSDT": {
      "dir": "short",
      "conf": 0.501
    },
    "DOTUSDT": {
      "dir": "short",
      "conf": 0.603
    },
    "AAVEUSDT": {
      "dir": "short",
      "conf": 0.514
    },
    "AVAXUSDT": {
      "dir": "short",
      "conf": 0.607
    },
    "NEARUSDT": {
      "dir": "short",
      "conf": 0.508
    },
    "ENAUSDT": {
      "dir": "short",
      "conf": 0.549
    },
    "UNIUSDT": {
      "dir": "short",
      "conf": 0.596
    },
    "STABLEUSDT": {
      "dir": "short",
      "conf": 0.592
    },
    "LTCUSDT": {
      "dir": "short",
      "conf": 0.607
    },
    "ZECUSDT": {
      "dir": "short",
      "conf": 0.512
    },
    "ARBUSDT": {
      "dir": "long",
      "conf": 0.632
    },
    "ALGOUSDT": {
      "dir": "short",
      "conf": 0.529
    },
    "TRUMPUSDT": {
      "dir": "short",
      "conf": 0.532
    },
    "WLDUSDT": {
      "dir": "long",
      "conf": 0.535
    },
    "BCHUSDT": {
      "dir": "short",
      "conf": 0.762
    },
    "XMRUSDT": {
      "dir": "long",
      "conf": 0.634
    },
    "TONUSDT": {
      "dir": "long",
      "conf": 0.504
    },
    "WLFIUSDT": {
      "dir": "short",
      "conf": 0.523
    },
    "DASHUSDT": {
      "dir": "long",
      "conf": 0.545
    },
    "RAVEUSDT": {
      "dir": "long",
      "conf": 0.754
    },
    "ASTERUSDT": {
      "dir": "long",
      "conf": 0.524
    },
    "SIRENUSDT": {
      "dir": "short",
      "conf": 0.563
    },
    "1000BONKUSDT": {
      "dir": "short",
      "conf": 0.529
    },
    "MUSDT": {
      "dir": "long",
      "conf": 0.525
    },
    "MNTUSDT": {
      "dir": "long",
      "conf": 0.504
    },
    "TRXUSDT": {
      "dir": "short",
      "conf": 0.606
    },
    "PENGUUSDT": {
      "dir": "long",
      "conf": 0.532
    }
  },
  "equity_hist": [
    {
      "t": "2026-04-14",
      "v": 664.4
    },
    {
      "t": "2026-04-15",
      "v": 605.46
    },
    {
      "t": "2026-04-16",
      "v": 1031.24
    },
    {
      "t": "2026-04-17",
      "v": 1373.66
    },
    {
      "t": "2026-04-18",
      "v": 1434.8
    },
    {
      "t": "2026-04-19",
      "v": 1362.33
    },
    {
      "t": "2026-04-20",
      "v": 1411.76
    },
    {
      "t": "2026-04-21",
      "v": 1665.55
    },
    {
      "t": "2026-04-22",
      "v": 1726.96
    },
    {
      "t": "2026-04-23",
      "v": 2433.14
    },
    {
      "t": "2026-04-24",
      "v": 2827.79
    },
    {
      "t": "2026-04-25",
      "v": 3139.96
    },
    {
      "t": "2026-04-26",
      "v": 3637.21
    },
    {
      "t": "2026-04-27",
      "v": 3345.4
    }
  ],
  "trade_history": [
    {
      "ts": "2026-04-27 13:07",
      "symbol": "AAVEUSDT",
      "side": "Buy",
      "pnl": 0.03,
      "reason": "마진 0.1USDT < 47"
    },
    {
      "ts": "2026-04-27 13:04",
      "symbol": "AAVEUSDT",
      "side": "Buy",
      "pnl": 97.01,
      "reason": "3/9"
    },
    {
      "ts": "2026-04-27 13:01",
      "symbol": "ENAUSDT",
      "side": "Buy",
      "pnl": 8.66,
      "reason": "3/11"
    },
    {
      "ts": "2026-04-27 12:33",
      "symbol": "ENAUSDT",
      "side": "Buy",
      "pnl": 15.24,
      "reason": "3/11"
    },
    {
      "ts": "2026-04-27 12:33",
      "symbol": "ENAUSDT",
      "side": "Buy",
      "pnl": 30.19,
      "reason": "3/11"
    },
    {
      "ts": "2026-04-27 12:33",
      "symbol": "ENAUSDT",
      "side": "Buy",
      "pnl": 0.99,
      "reason": "3/11"
    },
    {
      "ts": "2026-04-27 11:31",
      "symbol": "PENGUUSDT",
      "side": "Sell",
      "pnl": -619.87,
      "reason": "External Exit"
    },
    {
      "ts": "2026-04-27 10:17",
      "symbol": "ZECUSDT",
      "side": "Buy",
      "pnl": 22.18,
      "reason": "3/9"
    },
    {
      "ts": "2026-04-27 10:03",
      "symbol": "DOTUSDT",
      "side": "Sell",
      "pnl": -0.0,
      "reason": "L5"
    },
    {
      "ts": "2026-04-27 10:01",
      "symbol": "DOTUSDT",
      "side": "Sell",
      "pnl": -29.63,
      "reason": "5/9"
    },
    {
      "ts": "2026-04-27 10:00",
      "symbol": "SOLUSDT",
      "side": "Sell",
      "pnl": -136.8,
      "reason": "5/9"
    },
    {
      "ts": "2026-04-27 09:55",
      "symbol": "ZECUSDT",
      "side": "Buy",
      "pnl": 43.98,
      "reason": "3/9"
    },
    {
      "ts": "2026-04-27 09:55",
      "symbol": "ZECUSDT",
      "side": "Buy",
      "pnl": 86.25,
      "reason": "3/9"
    },
    {
      "ts": "2026-04-27 09:20",
      "symbol": "TAOUSDT",
      "side": "Buy",
      "pnl": 35.25,
      "reason": "-"
    },
    {
      "ts": "2026-04-27 07:38",
      "symbol": "ASTERUSDT",
      "side": "Buy",
      "pnl": 16.01,
      "reason": "1/9"
    },
    {
      "ts": "2026-04-27 07:24",
      "symbol": "ASTERUSDT",
      "side": "Buy",
      "pnl": 17.17,
      "reason": "2/9"
    },
    {
      "ts": "2026-04-27 05:21",
      "symbol": "ARBUSDT",
      "side": "Sell",
      "pnl": 0.0,
      "reason": "T1 진입 | GF=7 | Lv=8x | Seed=$9066(10.8%)"
    },
    {
      "ts": "2026-04-27 05:19",
      "symbol": "ARBUSDT",
      "side": "Sell",
      "pnl": 21.3,
      "reason": "4/9"
    },
    {
      "ts": "2026-04-27 05:02",
      "symbol": "TAOUSDT",
      "side": "Buy",
      "pnl": 70.62,
      "reason": "-"
    },
    {
      "ts": "2026-04-27 03:18",
      "symbol": "DOGEUSDT",
      "side": "Buy",
      "pnl": 16.34,
      "reason": "7/10"
    }
  ],
  "num_days": 27
}