{
  "ts": "2026-04-18T02:22:28.527530+09:00",
  "start_date": "2026-04-01",
  "status": "running",
  "equity": 31479.52,
  "available": 29533.81,
  "unrealized": 24.82,
  "daily_pnl": 68.36,
  "total_pnl": 1479.52,
  "cum_pct": 4.93,
  "daily_avg_pct": 0.2739,
  "annual_pct": 171.39,
  "mdd": -10.32,
  "current_dd": 0.0,
  "seed_used": 1945.71,
  "seed_used_pct": 6.18,
  "long_count": 3,
  "short_count": 3,
  "positions": [
    {
      "symbol": "WLFIUSDT",
      "side": "SHORT",
      "pnl": 11.02,
      "pnl_pct": 0.25,
      "margin": 630.44,
      "leverage": "7",
      "tier": "6/9",
      "entry": 0.0826,
      "mark": 0.0824
    },
    {
      "symbol": "HYPEUSDT",
      "side": "SHORT",
      "pnl": -11.59,
      "pnl_pct": -1.11,
      "margin": 149.59,
      "leverage": "7",
      "tier": "2/9",
      "entry": 44.0335,
      "mark": 44.521
    },
    {
      "symbol": "ADAUSDT",
      "side": "LONG",
      "pnl": -1.38,
      "pnl_pct": -0.14,
      "margin": 146.35,
      "leverage": "7",
      "tier": "3/10",
      "entry": 0.2636,
      "mark": 0.2632
    },
    {
      "symbol": "ZECUSDT",
      "side": "SHORT",
      "pnl": 24.31,
      "pnl_pct": 2.76,
      "margin": 110.15,
      "leverage": "8",
      "tier": "5/9",
      "entry": 345.5738,
      "mark": 336.04
    },
    {
      "symbol": "1000PEPEUSDT",
      "side": "LONG",
      "pnl": 5.09,
      "pnl_pct": 0.69,
      "margin": 105.68,
      "leverage": "7",
      "tier": "3/12",
      "entry": 0.004,
      "mark": 0.0041
    },
    {
      "symbol": "LINKUSDT",
      "side": "LONG",
      "pnl": -2.3,
      "pnl_pct": -0.44,
      "margin": 65.21,
      "leverage": "8",
      "tier": "2/10",
      "entry": 9.751,
      "mark": 9.708
    }
  ],
  "signals": {
    "BTCUSDT": {
      "dir": "short",
      "conf": 0.656
    },
    "XRPUSDT": {
      "dir": "short",
      "conf": 0.509
    },
    "SOLUSDT": {
      "dir": "short",
      "conf": 0.881
    },
    "LINKUSDT": {
      "dir": "long",
      "conf": 0.516
    },
    "1000PEPEUSDT": {
      "dir": "long",
      "conf": 0.543
    },
    "HYPEUSDT": {
      "dir": "long",
      "conf": 0.51
    },
    "ADAUSDT": {
      "dir": "long",
      "conf": 0.529
    },
    "SUIUSDT": {
      "dir": "short",
      "conf": 0.509
    },
    "ETHUSDT": {
      "dir": "long",
      "conf": 0.521
    },
    "DOGEUSDT": {
      "dir": "long",
      "conf": 0.51
    },
    "TAOUSDT": {
      "dir": "short",
      "conf": 0.543
    },
    "BNBUSDT": {
      "dir": "short",
      "conf": 0.521
    },
    "DOTUSDT": {
      "dir": "short",
      "conf": 0.557
    },
    "AAVEUSDT": {
      "dir": "short",
      "conf": 0.549
    },
    "AVAXUSDT": {
      "dir": "short",
      "conf": 0.598
    },
    "NEARUSDT": {
      "dir": "short",
      "conf": 0.505
    },
    "ENAUSDT": {
      "dir": "short",
      "conf": 0.575
    },
    "UNIUSDT": {
      "dir": "short",
      "conf": 0.596
    },
    "STABLEUSDT": {
      "dir": "long",
      "conf": 0.617
    },
    "LTCUSDT": {
      "dir": "short",
      "conf": 0.51
    },
    "ZECUSDT": {
      "dir": "short",
      "conf": 0.64
    },
    "ARBUSDT": {
      "dir": "short",
      "conf": 0.513
    },
    "ALGOUSDT": {
      "dir": "short",
      "conf": 0.529
    },
    "TRUMPUSDT": {
      "dir": "short",
      "conf": 0.587
    },
    "WLDUSDT": {
      "dir": "long",
      "conf": 0.526
    },
    "BCHUSDT": {
      "dir": "long",
      "conf": 0.873
    },
    "XMRUSDT": {
      "dir": "short",
      "conf": 0.567
    },
    "TONUSDT": {
      "dir": "long",
      "conf": 0.504
    },
    "WLFIUSDT": {
      "dir": "short",
      "conf": 0.58
    },
    "DASHUSDT": {
      "dir": "long",
      "conf": 0.545
    },
    "RAVEUSDT": {
      "dir": "long",
      "conf": 0.754
    },
    "ASTERUSDT": {
      "dir": "long",
      "conf": 0.534
    },
    "SIRENUSDT": {
      "dir": "short",
      "conf": 0.567
    },
    "1000BONKUSDT": {
      "dir": "short",
      "conf": 0.529
    }
  },
  "equity_hist": [
    {
      "t": "2026-04-14",
      "v": 664.4
    },
    {
      "t": "2026-04-15",
      "v": 605.46
    },
    {
      "t": "2026-04-16",
      "v": 1031.24
    },
    {
      "t": "2026-04-17",
      "v": 1373.66
    },
    {
      "t": "2026-04-18",
      "v": 1479.52
    }
  ],
  "trade_history": [
    {
      "ts": "2026-04-18 02:18",
      "symbol": "ZECUSDT",
      "side": "Sell",
      "pnl": 15.89,
      "reason": "5/9"
    },
    {
      "ts": "2026-04-18 02:15",
      "symbol": "ZECUSDT",
      "side": "Sell",
      "pnl": 25.66,
      "reason": "-"
    },
    {
      "ts": "2026-04-18 00:27",
      "symbol": "1000BONKUSDT",
      "side": "Buy",
      "pnl": 17.17,
      "reason": "5/11"
    },
    {
      "ts": "2026-04-18 00:08",
      "symbol": "AVAXUSDT",
      "side": "Buy",
      "pnl": 0.02,
      "reason": "L2"
    },
    {
      "ts": "2026-04-18 00:03",
      "symbol": "AVAXUSDT",
      "side": "Buy",
      "pnl": 9.62,
      "reason": "3/10"
    },
    {
      "ts": "2026-04-17 23:54",
      "symbol": "WLDUSDT",
      "side": "Buy",
      "pnl": 1.29,
      "reason": "1/12"
    },
    {
      "ts": "2026-04-17 23:00",
      "symbol": "WLDUSDT",
      "side": "Buy",
      "pnl": 2.36,
      "reason": "1/12"
    },
    {
      "ts": "2026-04-17 22:58",
      "symbol": "WLDUSDT",
      "side": "Buy",
      "pnl": 5.29,
      "reason": "-"
    },
    {
      "ts": "2026-04-17 22:55",
      "symbol": "BTCUSDT",
      "side": "Buy",
      "pnl": 5.43,
      "reason": "1/9"
    },
    {
      "ts": "2026-04-17 22:34",
      "symbol": "BTCUSDT",
      "side": "Buy",
      "pnl": 2.83,
      "reason": "2/9"
    },
    {
      "ts": "2026-04-17 22:31",
      "symbol": "ENAUSDT",
      "side": "Buy",
      "pnl": 8.98,
      "reason": "3/11"
    },
    {
      "ts": "2026-04-17 22:26",
      "symbol": "AVAXUSDT",
      "side": "Buy",
      "pnl": 11.97,
      "reason": "3/10"
    },
    {
      "ts": "2026-04-17 22:26",
      "symbol": "AVAXUSDT",
      "side": "Buy",
      "pnl": 23.69,
      "reason": "3/10"
    },
    {
      "ts": "2026-04-17 22:12",
      "symbol": "1000BONKUSDT",
      "side": "Buy",
      "pnl": 14.63,
      "reason": "3/11"
    },
    {
      "ts": "2026-04-17 22:12",
      "symbol": "1000BONKUSDT",
      "side": "Buy",
      "pnl": 29.23,
      "reason": "3/11"
    },
    {
      "ts": "2026-04-17 22:12",
      "symbol": "ENAUSDT",
      "side": "Buy",
      "pnl": 8.76,
      "reason": "3/11"
    },
    {
      "ts": "2026-04-17 22:11",
      "symbol": "ENAUSDT",
      "side": "Buy",
      "pnl": 16.6,
      "reason": "3/11"
    },
    {
      "ts": "2026-04-17 20:24",
      "symbol": "TAOUSDT",
      "side": "Buy",
      "pnl": 5.55,
      "reason": "6/11"
    },
    {
      "ts": "2026-04-17 20:18",
      "symbol": "TAOUSDT",
      "side": "Buy",
      "pnl": 10.39,
      "reason": "6/11"
    },
    {
      "ts": "2026-04-17 20:18",
      "symbol": "TAOUSDT",
      "side": "Buy",
      "pnl": 20.01,
      "reason": "6/11"
    }
  ],
  "num_days": 18
}