{
  "ts": "2026-06-13T09:48:41.704782+09:00",
  "start_date": "2026-04-01",
  "status": "running",
  "equity": 15623.37,
  "available": 12029.29,
  "unrealized": 36.98,
  "daily_pnl": -203.65,
  "total_pnl": 623.37,
  "cum_pct": 4.16,
  "daily_avg_pct": 0.0551,
  "annual_pct": 22.27,
  "mdd": -7.67,
  "current_dd": -6.81,
  "seed_used": 3594.08,
  "seed_used_pct": 23.0,
  "long_count": 1,
  "short_count": 1,
  "positions": [
    {
      "symbol": "HYPEUSDT",
      "side": "LONG",
      "pnl": 9.97,
      "pnl_pct": 0.05,
      "margin": 2185.58,
      "leverage": "10",
      "tier": "1/1",
      "entry": 59.169,
      "mark": 59.196
    },
    {
      "symbol": "1000PEPEUSDT",
      "side": "SHORT",
      "pnl": 27.23,
      "pnl_pct": 0.49,
      "margin": 1395.44,
      "leverage": "4",
      "tier": "1/1",
      "entry": 0.0028,
      "mark": 0.0028
    }
  ],
  "signals": {
    "BTCUSDT": {
      "dir": "short",
      "conf": 0.385
    },
    "XRPUSDT": {
      "dir": "short",
      "conf": 0.567
    },
    "SOLUSDT": {
      "dir": "neutral",
      "conf": 0.368
    },
    "LINKUSDT": {
      "dir": "long",
      "conf": 0.397
    },
    "1000PEPEUSDT": {
      "dir": "long",
      "conf": 0.463
    },
    "HYPEUSDT": {
      "dir": "short",
      "conf": 0.551
    },
    "ADAUSDT": {
      "dir": "short",
      "conf": 0.531
    },
    "SUIUSDT": {
      "dir": "short",
      "conf": 0.504
    },
    "ETHUSDT": {
      "dir": "short",
      "conf": 0.461
    },
    "DOGEUSDT": {
      "dir": "neutral",
      "conf": 0.45
    },
    "TAOUSDT": {
      "dir": "short",
      "conf": 0.509
    },
    "BNBUSDT": {
      "dir": "neutral",
      "conf": 0.361
    },
    "DOTUSDT": {
      "dir": "long",
      "conf": 0.507
    },
    "AAVEUSDT": {
      "dir": "long",
      "conf": 0.44
    },
    "AVAXUSDT": {
      "dir": "neutral",
      "conf": 0.43
    },
    "NEARUSDT": {
      "dir": "short",
      "conf": 0.498
    },
    "ENAUSDT": {
      "dir": "short",
      "conf": 0.537
    },
    "UNIUSDT": {
      "dir": "short",
      "conf": 0.596
    },
    "STABLEUSDT": {
      "dir": "short",
      "conf": 0.592
    },
    "LTCUSDT": {
      "dir": "long",
      "conf": 0.5
    },
    "ZECUSDT": {
      "dir": "long",
      "conf": 0.474
    },
    "ARBUSDT": {
      "dir": "short",
      "conf": 0.643
    },
    "ALGOUSDT": {
      "dir": "short",
      "conf": 0.529
    },
    "TRUMPUSDT": {
      "dir": "short",
      "conf": 0.449
    },
    "WLDUSDT": {
      "dir": "long",
      "conf": 0.479
    },
    "BCHUSDT": {
      "dir": "short",
      "conf": 0.491
    },
    "XMRUSDT": {
      "dir": "short",
      "conf": 0.691
    },
    "TONUSDT": {
      "dir": "short",
      "conf": 0.512
    },
    "WLFIUSDT": {
      "dir": "short",
      "conf": 0.524
    },
    "DASHUSDT": {
      "dir": "short",
      "conf": 0.813
    },
    "RAVEUSDT": {
      "dir": "long",
      "conf": 0.754
    },
    "ASTERUSDT": {
      "dir": "short",
      "conf": 0.628
    },
    "SIRENUSDT": {
      "dir": "short",
      "conf": 0.573
    },
    "1000BONKUSDT": {
      "dir": "short",
      "conf": 0.529
    },
    "MUSDT": {
      "dir": "long",
      "conf": 0.51
    },
    "MNTUSDT": {
      "dir": "long",
      "conf": 0.504
    },
    "TRXUSDT": {
      "dir": "short",
      "conf": 0.557
    },
    "PENGUUSDT": {
      "dir": "short",
      "conf": 0.601
    },
    "APTUSDT": {
      "dir": "short",
      "conf": 0.696
    },
    "ONDOUSDT": {
      "dir": "short",
      "conf": 0.482
    },
    "ICPUSDT": {
      "dir": "short",
      "conf": 0.384
    },
    "1000LUNCUSDT": {
      "dir": "long",
      "conf": 0.617
    },
    "FILUSDT": {
      "dir": "long",
      "conf": 0.558
    },
    "VIRTUALUSDT": {
      "dir": "long",
      "conf": 0.528
    },
    "VVVUSDT": {
      "dir": "long",
      "conf": 0.501
    },
    "BUSDT": {
      "dir": "short",
      "conf": 0.452
    },
    "INJUSDT": {
      "dir": "long",
      "conf": 0.527
    },
    "RENDERUSDT": {
      "dir": "long",
      "conf": 0.459
    },
    "LABUSDT": {
      "dir": "long",
      "conf": 1.0
    },
    "HUSDT": {
      "dir": "long",
      "conf": 0.599
    },
    "BEATUSDT": {
      "dir": "long",
      "conf": 0.589
    },
    "VELVETUSDT": {
      "dir": "long",
      "conf": 0.897
    }
  },
  "equity_hist": [
    {
      "t": "2026-05-13",
      "v": -10.78
    },
    {
      "t": "2026-05-14",
      "v": 42.28
    },
    {
      "t": "2026-05-15",
      "v": 46.15
    },
    {
      "t": "2026-05-16",
      "v": 158.46
    },
    {
      "t": "2026-05-17",
      "v": 145.26
    },
    {
      "t": "2026-05-18",
      "v": 278.09
    },
    {
      "t": "2026-05-19",
      "v": 278.32
    },
    {
      "t": "2026-05-20",
      "v": 246.77
    },
    {
      "t": "2026-05-21",
      "v": 276.96
    },
    {
      "t": "2026-05-22",
      "v": 351.46
    },
    {
      "t": "2026-05-23",
      "v": 483.89
    },
    {
      "t": "2026-05-24",
      "v": 647.23
    },
    {
      "t": "2026-05-25",
      "v": 483.78
    },
    {
      "t": "2026-05-26",
      "v": 486.96
    },
    {
      "t": "2026-05-27",
      "v": 357.39
    },
    {
      "t": "2026-05-28",
      "v": 509.27
    },
    {
      "t": "2026-05-29",
      "v": 809.06
    },
    {
      "t": "2026-05-30",
      "v": 607.59
    },
    {
      "t": "2026-05-31",
      "v": 748.22
    },
    {
      "t": "2026-06-01",
      "v": 1014.93
    },
    {
      "t": "2026-06-02",
      "v": 1215.41
    },
    {
      "t": "2026-06-03",
      "v": 1100.21
    },
    {
      "t": "2026-06-04",
      "v": 1334.03
    },
    {
      "t": "2026-06-05",
      "v": 1581.46
    },
    {
      "t": "2026-06-06",
      "v": 1500.0
    },
    {
      "t": "2026-06-07",
      "v": 1495.16
    },
    {
      "t": "2026-06-08",
      "v": 944.66
    },
    {
      "t": "2026-06-09",
      "v": 1016.34
    },
    {
      "t": "2026-06-10",
      "v": 647.46
    },
    {
      "t": "2026-06-11",
      "v": 1881.31
    },
    {
      "t": "2026-06-12",
      "v": 663.72
    },
    {
      "t": "2026-06-13",
      "v": 623.37
    }
  ],
  "trade_history": [
    {
      "ts": "2026-06-13 04:18",
      "symbol": "1000PEPEUSDT",
      "side": "Buy",
      "pnl": -3.74,
      "reason": "1/1"
    },
    {
      "ts": "2026-06-13 03:57",
      "symbol": "1000PEPEUSDT",
      "side": "Buy",
      "pnl": -13.69,
      "reason": "1/1"
    },
    {
      "ts": "2026-06-13 00:13",
      "symbol": "ADAUSDT",
      "side": "Sell",
      "pnl": -186.22,
      "reason": "1/1"
    },
    {
      "ts": "2026-06-12 23:11",
      "symbol": "XMRUSDT",
      "side": "Sell",
      "pnl": -346.08,
      "reason": "External Exit"
    },
    {
      "ts": "2026-06-12 21:39",
      "symbol": "VELVETUSDT",
      "side": "Buy",
      "pnl": -70.7,
      "reason": "External Exit"
    },
    {
      "ts": "2026-06-12 21:10",
      "symbol": "LABUSDT",
      "side": "Buy",
      "pnl": -18.9,
      "reason": "1/2"
    },
    {
      "ts": "2026-06-12 20:37",
      "symbol": "LABUSDT",
      "side": "Buy",
      "pnl": 196.67,
      "reason": "-"
    },
    {
      "ts": "2026-06-12 20:30",
      "symbol": "LABUSDT",
      "side": "Buy",
      "pnl": 280.96,
      "reason": "-"
    },
    {
      "ts": "2026-06-12 19:30",
      "symbol": "VELVETUSDT",
      "side": "Buy",
      "pnl": -249.48,
      "reason": "2/2"
    },
    {
      "ts": "2026-06-12 17:11",
      "symbol": "VELVETUSDT",
      "side": "Buy",
      "pnl": -8.73,
      "reason": "1/2"
    },
    {
      "ts": "2026-06-12 16:05",
      "symbol": "VELVETUSDT",
      "side": "Buy",
      "pnl": 30.38,
      "reason": "-"
    },
    {
      "ts": "2026-06-12 16:01",
      "symbol": "VELVETUSDT",
      "side": "Buy",
      "pnl": 43.17,
      "reason": "-"
    },
    {
      "ts": "2026-06-12 03:13",
      "symbol": "LABUSDT",
      "side": "Buy",
      "pnl": -860.11,
      "reason": "2/2"
    },
    {
      "ts": "2026-06-12 02:48",
      "symbol": "SOLUSDT",
      "side": "Sell",
      "pnl": -133.95,
      "reason": "External Exit"
    },
    {
      "ts": "2026-06-12 00:22",
      "symbol": "LABUSDT",
      "side": "Buy",
      "pnl": 72.98,
      "reason": "2/2"
    },
    {
      "ts": "2026-06-11 23:30",
      "symbol": "LABUSDT",
      "side": "Buy",
      "pnl": 604.21,
      "reason": "2/2"
    },
    {
      "ts": "2026-06-11 23:29",
      "symbol": "LABUSDT",
      "side": "Buy",
      "pnl": 296.9,
      "reason": "-"
    },
    {
      "ts": "2026-06-11 20:11",
      "symbol": "HYPEUSDT",
      "side": "Buy",
      "pnl": 265.07,
      "reason": "External Exit"
    },
    {
      "ts": "2026-06-11 20:06",
      "symbol": "HYPEUSDT",
      "side": "Buy",
      "pnl": 106.41,
      "reason": "-"
    },
    {
      "ts": "2026-06-11 12:32",
      "symbol": "ENAUSDT",
      "side": "Sell",
      "pnl": -319.91,
      "reason": "External Exit"
    }
  ],
  "num_days": 74
}