{
  "ts": "2026-04-02T03:04:44.634910+09:00",
  "start_date": "2026-04-01",
  "status": "running",
  "equity": 10019.13,
  "available": 9586.3,
  "unrealized": 4.33,
  "daily_pnl": 11.39,
  "total_pnl": 19.13,
  "cum_pct": 0.19,
  "daily_avg_pct": 0.095,
  "annual_pct": 41.42,
  "mdd": -0.54,
  "current_dd": -0.09,
  "seed_used": 432.83,
  "seed_used_pct": 4.32,
  "long_count": 5,
  "short_count": 3,
  "positions": [
    {
      "symbol": "SOLUSDT",
      "side": "LONG",
      "pnl": -2.37,
      "pnl_pct": -0.33,
      "margin": 79.69,
      "leverage": "9",
      "tier": "3/11",
      "entry": 84.3819,
      "mark": 84.103
    },
    {
      "symbol": "XRPUSDT",
      "side": "SHORT",
      "pnl": 1.5,
      "pnl_pct": 0.25,
      "margin": 58.91,
      "leverage": "10",
      "tier": "2/9",
      "entry": 1.3512,
      "mark": 1.3478
    },
    {
      "symbol": "BTCUSDT",
      "side": "LONG",
      "pnl": -1.16,
      "pnl_pct": -0.14,
      "margin": 54.47,
      "leverage": "15",
      "tier": "2/9",
      "entry": 68090.7833,
      "mark": 67993.8
    },
    {
      "symbol": "SUIUSDT",
      "side": "LONG",
      "pnl": -1.45,
      "pnl_pct": -0.26,
      "margin": 51.49,
      "leverage": "11",
      "tier": "3/10",
      "entry": 0.899,
      "mark": 0.8967
    },
    {
      "symbol": "AAVEUSDT",
      "side": "SHORT",
      "pnl": 5.13,
      "pnl_pct": 1.26,
      "margin": 45.33,
      "leverage": "9",
      "tier": "4/10",
      "entry": 100.231,
      "mark": 98.97
    },
    {
      "symbol": "BNBUSDT",
      "side": "SHORT",
      "pnl": 1.96,
      "pnl_pct": 0.75,
      "margin": 28.81,
      "leverage": "9",
      "tier": "2/9",
      "entry": 617.3554,
      "mark": 612.7
    },
    {
      "symbol": "ADAUSDT",
      "side": "LONG",
      "pnl": 0.28,
      "pnl_pct": 0.12,
      "margin": 22.82,
      "leverage": "10",
      "tier": "1/10",
      "entry": 0.2489,
      "mark": 0.2492
    },
    {
      "symbol": "LINKUSDT",
      "side": "LONG",
      "pnl": 0.46,
      "pnl_pct": 0.34,
      "margin": 22.65,
      "leverage": "6",
      "tier": "2/10",
      "entry": 8.942,
      "mark": 8.972
    }
  ],
  "signals": {
    "BTCUSDT": {
      "dir": "long",
      "conf": 0.978
    },
    "ETHUSDT": {
      "dir": "short",
      "conf": 0.711
    },
    "SOLUSDT": {
      "dir": "long",
      "conf": 0.843
    },
    "XRPUSDT": {
      "dir": "long",
      "conf": 0.523
    },
    "DOGEUSDT": {
      "dir": "short",
      "conf": 0.72
    },
    "HYPEUSDT": {
      "dir": "long",
      "conf": 0.658
    },
    "TAOUSDT": {
      "dir": "long",
      "conf": 0.509
    },
    "ADAUSDT": {
      "dir": "long",
      "conf": 0.749
    },
    "ZECUSDT": {
      "dir": "short",
      "conf": 0.54
    },
    "1000PEPEUSDT": {
      "dir": "short",
      "conf": 0.939
    },
    "SUIUSDT": {
      "dir": "long",
      "conf": 0.785
    },
    "LINKUSDT": {
      "dir": "long",
      "conf": 0.627
    },
    "ENAUSDT": {
      "dir": "short",
      "conf": 0.51
    },
    "DOTUSDT": {
      "dir": "short",
      "conf": 0.642
    },
    "BCHUSDT": {
      "dir": "long",
      "conf": 0.59
    },
    "AVAXUSDT": {
      "dir": "short",
      "conf": 0.551
    },
    "AAVEUSDT": {
      "dir": "long",
      "conf": 0.729
    },
    "NEARUSDT": {
      "dir": "short",
      "conf": 0.542
    },
    "BNBUSDT": {
      "dir": "long",
      "conf": 0.701
    }
  },
  "equity_hist": [
    {
      "t": "2026-04-01",
      "v": 0.61
    },
    {
      "t": "2026-04-02",
      "v": 12.0
    }
  ],
  "trade_history": [
    {
      "ts": "2026-04-02 03:04",
      "symbol": "BNBUSDT",
      "side": "Sell",
      "pnl": 0.05,
      "reason": "2/9"
    },
    {
      "ts": "2026-04-02 03:03",
      "symbol": "ADAUSDT",
      "side": "Sell",
      "pnl": 1.84,
      "reason": "4/10"
    },
    {
      "ts": "2026-04-02 02:49",
      "symbol": "SOLUSDT",
      "side": "Sell",
      "pnl": -0.01,
      "reason": "마진 0.9USDT &lt; 5"
    },
    {
      "ts": "2026-04-02 02:48",
      "symbol": "BTCUSDT",
      "side": "Sell",
      "pnl": 1.17,
      "reason": "3/9"
    },
    {
      "ts": "2026-04-02 02:46",
      "symbol": "AAVEUSDT",
      "side": "Sell",
      "pnl": 2.04,
      "reason": "4/10"
    },
    {
      "ts": "2026-04-02 02:46",
      "symbol": "ADAUSDT",
      "side": "Sell",
      "pnl": 0.72,
      "reason": "5/10"
    },
    {
      "ts": "2026-04-02 02:44",
      "symbol": "SOLUSDT",
      "side": "Sell",
      "pnl": -0.8,
      "reason": "5/10"
    },
    {
      "ts": "2026-04-02 02:43",
      "symbol": "SUIUSDT",
      "side": "Sell",
      "pnl": 2.21,
      "reason": "3/10"
    },
    {
      "ts": "2026-04-02 02:32",
      "symbol": "BTCUSDT",
      "side": "Sell",
      "pnl": 0.43,
      "reason": "4/9"
    },
    {
      "ts": "2026-04-02 02:27",
      "symbol": "SOLUSDT",
      "side": "Sell",
      "pnl": 1.49,
      "reason": "6/10"
    },
    {
      "ts": "2026-04-02 02:26",
      "symbol": "SUIUSDT",
      "side": "Sell",
      "pnl": 0.58,
      "reason": "4/10"
    },
    {
      "ts": "2026-04-02 00:21",
      "symbol": "ETHUSDT",
      "side": "Buy",
      "pnl": -0.1,
      "reason": "2/10"
    },
    {
      "ts": "2026-04-02 00:04",
      "symbol": "1000PEPEUSDT",
      "side": "Buy",
      "pnl": 1.81,
      "reason": "2/10"
    },
    {
      "ts": "2026-04-02 00:02",
      "symbol": "ETHUSDT",
      "side": "Buy",
      "pnl": -0.03,
      "reason": "3/10"
    },
    {
      "ts": "2026-04-01 23:46",
      "symbol": "1000PEPEUSDT",
      "side": "Buy",
      "pnl": 1.89,
      "reason": "3/10"
    },
    {
      "ts": "2026-04-01 22:09",
      "symbol": "SUIUSDT",
      "side": "Sell",
      "pnl": -0.94,
      "reason": "마진 22.6USDT < 100"
    },
    {
      "ts": "2026-04-01 22:09",
      "symbol": "AAVEUSDT",
      "side": "Sell",
      "pnl": -0.44,
      "reason": "마진 22.6USDT < 100"
    },
    {
      "ts": "2026-04-01 22:09",
      "symbol": "1000PEPEUSDT",
      "side": "Buy",
      "pnl": 0.18,
      "reason": "마진 22.8USDT < 100"
    },
    {
      "ts": "2026-04-01 22:09",
      "symbol": "ETHUSDT",
      "side": "Buy",
      "pnl": 0.23,
      "reason": "마진 21.1USDT < 100"
    },
    {
      "ts": "2026-04-01 22:09",
      "symbol": "BNBUSDT",
      "side": "Sell",
      "pnl": -0.31,
      "reason": "마진 24.6USDT < 100"
    }
  ],
  "num_days": 2
}